[
{
  "model": "auth.user",
  "pk": 1,
  "fields": {
    "password": "pbkdf2_sha256$390000$SZbWUQMOnbGxYOU3BzwO4O$9nP3SNuNtWfzeLOjo9jY+uuxRvZhzD1njruL7yP8MO0=",
    "last_login": "2022-09-19T18:49:10.783Z",
    "is_superuser": true,
    "username": "admin",
    "first_name": "",
    "last_name": "",
    "email": "admin@example.com",
    "is_staff": true,
    "is_active": true,
    "date_joined": "2022-09-05T16:42:45.852Z",
    "groups": [],
    "user_permissions": []
  }
},
{
  "model": "auth.user",
  "pk": 2,
  "fields": {
    "password": "pbkdf2_sha256$390000$7ZLeMaFnMgdIxLi7073BZU$Y5D/sfaILiT8CZ2iE+kdAmOrZUGzjQSCQlVz0O0WOHw=",
    "last_login": "2022-09-19T17:05:10.138Z",
    "is_superuser": false,
    "username": "harry",
    "first_name": "Harry",
    "last_name": "",
    "email": "harry@hackerone.com",
    "is_staff": false,
    "is_active": true,
    "date_joined": "2022-09-18T17:49:57.574Z",
    "groups": [],
    "user_permissions": []
  }
},
{
  "model": "auth.user",
  "pk": 4,
  "fields": {
    "password": "pbkdf2_sha256$390000$I4ZBfjxOU4ibuyB7Bb3nGD$mLwCR4WoRxwBMt1DrL18svRQ1ExrXTgjYjEK4T4Syt0=",
    "last_login": "2022-09-20T12:12:44.696Z",
    "is_superuser": false,
    "username": "demo2",
    "first_name": "Demo2",
    "last_name": "",
    "email": "demo2@example.com",
    "is_staff": false,
    "is_active": true,
    "date_joined": "2022-09-19T17:27:42.711Z",
    "groups": [],
    "user_permissions": []
  }
},
{
  "model": "auth.user",
  "pk": 6,
  "fields": {
    "password": "pbkdf2_sha256$390000$JWN1m6x2mPpVk3DGO5GwMY$H/VQwyNcJN/3CHe3DMfZbqsIvyCuyE779pbMTX5zpIQ=",
    "last_login": "2022-09-20T12:12:27.188Z",
    "is_superuser": false,
    "username": "demo3",
    "first_name": "demo3",
    "last_name": "",
    "email": "demo3@example.com",
    "is_staff": false,
    "is_active": true,
    "date_joined": "2022-09-19T19:07:53.789Z",
    "groups": [],
    "user_permissions": []
  }
},
{
  "model": "auth.user",
  "pk": 7,
  "fields": {
    "password": "pbkdf2_sha256$390000$ER13UPYpXLCD78os3y58TH$97+gluyBtQLLaXrdUZonB2/4VyGsemoYwrdCPDbHUHg=",
    "last_login": "2022-09-25T11:41:34.202Z",
    "is_superuser": true,
    "username": "Admin1",
    "first_name": "",
    "last_name": "",
    "email": "admin1@example.com",
    "is_staff": true,
    "is_active": true,
    "date_joined": "2022-09-25T11:39:19.148Z",
    "groups": [],
    "user_permissions": []
  }
}
]
